hakai_segmentation/__init__.py
hakai_segmentation/cli.py
hakai_segmentation/lib.py
hakai_segmentation/managers.py
hakai_segmentation/models.py
hakai_segmentation/utils.py
hakai_segmentation/data/LRASPP_MobileNetV3_kelp_presence_jit.pt
hakai_segmentation/data/LRASPP_MobileNetV3_kelp_species_jit_miou=0.9634.pt
hakai_segmentation/data/LRASPP_MobileNetV3_mussel_presence_jit_v2.pt
hakai_segmentation/data/__init__.py
hakai_segmentation/geotiff_io/__init__.py
hakai_segmentation/geotiff_io/geotiff_reader.py
hakai_segmentation/geotiff_io/geotiff_writer.py
hakai_segmentation-0.4.1.dist-info/LICENSE.txt
hakai_segmentation-0.4.1.dist-info/METADATA
hakai_segmentation-0.4.1.dist-info/WHEEL
hakai_segmentation-0.4.1.dist-info/entry_points.txt
hakai_segmentation-0.4.1.dist-info/top_level.txt
hakai_segmentation-0.4.1.dist-info/RECORD
