Metadata-Version: 2.1
Name: hakai-segmentation
Version: 0.4.1
Summary: Segmentation Tools for Remotely Sensed RPAS Imagery
Home-page: https://github.com/hakaiInstitute/hakai-segmentation
Author: Taylor Denouden
Author-email: taylordenouden@gmail.com
License: UNKNOWN
Platform: UNKNOWN
Requires-Python: ~=3.7,<3.10
License-File: LICENSE.txt
Requires-Dist: typer (~=0.4)
Requires-Dist: numpy (~=1.16)
Requires-Dist: torch (~=1.10)
Requires-Dist: rasterio (~=1.2)
Requires-Dist: torchvision (~=0.11)
Requires-Dist: tqdm (~=4.62)
